ip2location_csv_converter/__init__.py
ip2location_csv_converter/commandline.py
ip2location_csv_converter/ip2location_csv_converter.py
ip2location_python_csv_converter-1.4.0.dist-info/licenses/license.txt
ip2location_python_csv_converter-1.4.0.dist-info/METADATA
ip2location_python_csv_converter-1.4.0.dist-info/WHEEL
ip2location_python_csv_converter-1.4.0.dist-info/entry_points.txt
ip2location_python_csv_converter-1.4.0.dist-info/top_level.txt
ip2location_python_csv_converter-1.4.0.dist-info/RECORD
